Trough/__init__.py
Trough/Trough_Control/__init__.py
Trough/Trough_Control/message_utils.py
Trough/Trough_Control/simulation.py
Trough/Trough_Control/trough_util.py
Trough/Trough_GUI/Collect_data.py
Trough/Trough_GUI/Monitor_Calibrate.py
Trough/Trough_GUI/__init__.py
Trough/Trough_GUI/calibration_utils.py
Trough/Trough_GUI/command_widgets.py
Trough/Trough_GUI/conversions.py
Trough/Trough_GUI/status_widgets.py
Trough_Control/__init__.py
Trough_Control/error_tolerant.py
Trough_Control/init_trough.py
Trough_Control/message_utils.py
Trough_Control/simulation.py
Trough_Control/trough_util.py
Trough_GUI/Collect_data.py
Trough_GUI/Monitor_Calibrate.py
Trough_GUI/__init__.py
Trough_GUI/calibration_utils.py
Trough_GUI/command_widgets.py
Trough_GUI/conversions.py
Trough_GUI/status_widgets.py
langmuir_trough-0.8.1.dist-info/METADATA
langmuir_trough-0.8.1.dist-info/WHEEL
langmuir_trough-0.8.1.dist-info/top_level.txt
langmuir_trough-0.8.1.dist-info/RECORD
