Metadata-Version: 2.1
Name: langmuir-trough
Version: 0.8.1
Summary: Controls and collects data from Gutow Lab Langmuir Trough.
Home-page: https://github.com/gutow/Langmuir_Trough.git
Author: Jonathan Gutow
Author-email: gutow@uwosh.edu
License: GPL-3.0+
Classifier: Development Status :: 4 - Beta
Classifier: Intended Audience :: Developers
Classifier: Intended Audience :: Education
Classifier: License :: OSI Approved :: GNU General Public License v3 or later (GPLv3+)
Classifier: Programming Language :: Python :: 3
Classifier: Programming Language :: JavaScript
Classifier: Operating System :: OS Independent
Requires-Dist: ipywidgets (<8.0,>=7.6.2)
Requires-Dist: JPSLUtils (>=0.7.0)
Requires-Dist: JPSLMenus (>=0.5.0)
Requires-Dist: lmfit (>=1.0.3)
Requires-Dist: round-using-error (>=1.1.1)
Requires-Dist: pi-plates (>=7.21)
Requires-Dist: numpy (>=1.21)
Requires-Dist: plotly (>=5.8.2)
Requires-Dist: jupyter (>=1.0.0)
Requires-Dist: jupyterlab (>=3.6.1)
Requires-Dist: notebook (>=6.4.12)
Requires-Dist: jupyter-contrib-nbextensions (>=0.5.1)
Requires-Dist: pandas (>=1.4.2)
Requires-Dist: jupyter-pandas-GUI (>=0.7.0)
Requires-Dist: AdvancedHTMLParser (>=9.0.1)
Requires-Dist: RPi.GPIO (>=0.7.0) ; platform_system == "Linux"
Requires-Dist: spidev (>=3.5) ; platform_system == "Linux"
